zemfrog/__init__.py
zemfrog/app.py
zemfrog/cli.py
zemfrog/decorators.py
zemfrog/exception.py
zemfrog/generator.py
zemfrog/globals.py
zemfrog/helper.py
zemfrog/mixins.py
zemfrog/models.py
zemfrog/repl.py
zemfrog/scaffold.py
zemfrog/tasks.py
zemfrog/validators.py
zemfrog/commands/__init__.py
zemfrog/commands/api.py
zemfrog/commands/app.py
zemfrog/commands/blueprint.py
zemfrog/commands/command.py
zemfrog/commands/context.py
zemfrog/commands/errorhandler.py
zemfrog/commands/extension.py
zemfrog/commands/filter.py
zemfrog/commands/loader.py
zemfrog/commands/middleware.py
zemfrog/commands/model.py
zemfrog/commands/permission.py
zemfrog/commands/role.py
zemfrog/commands/secretkey.py
zemfrog/commands/task.py
zemfrog/commands/user.py
zemfrog/extensions/__init__.py
zemfrog/extensions/celery.py
zemfrog/extensions/cors.py
zemfrog/extensions/jwt.py
zemfrog/extensions/mail.py
zemfrog/extensions/marshmallow.py
zemfrog/extensions/migrate.py
zemfrog/extensions/smorest.py
zemfrog/extensions/sqlalchemy.py
zemfrog/handlers/__init__.py
zemfrog/handlers/api_errors.py
zemfrog/loaders/__init__.py
zemfrog/loaders/api.py
zemfrog/loaders/blueprint.py
zemfrog/loaders/command.py
zemfrog/loaders/context_processor.py
zemfrog/loaders/error_handler.py
zemfrog/loaders/extension.py
zemfrog/loaders/jinja_filter.py
zemfrog/loaders/middleware.py
zemfrog/loaders/model.py
zemfrog/loaders/multiapp.py
zemfrog/loaders/staticfile.py
zemfrog/loaders/task.py
zemfrog/templates/api/name.py
zemfrog/templates/blueprint/__init__.py
zemfrog/templates/blueprint/routes.py
zemfrog/templates/blueprint/urls.py
zemfrog/templates/blueprint/views.py
zemfrog/templates/blueprint/static/.gitkeep
zemfrog/templates/blueprint/templates/.gitkeep
zemfrog/templates/command/name.py
zemfrog/templates/context/name.py
zemfrog/templates/crud/name.py
zemfrog/templates/errorhandler/name.py
zemfrog/templates/extension/name.py
zemfrog/templates/filter/name.py
zemfrog/templates/loader/name.py
zemfrog/templates/middleware/name.py
zemfrog-5.0.1.dist-info/AUTHORS.rst
zemfrog-5.0.1.dist-info/LICENSE
zemfrog-5.0.1.dist-info/METADATA
zemfrog-5.0.1.dist-info/WHEEL
zemfrog-5.0.1.dist-info/entry_points.txt
zemfrog-5.0.1.dist-info/top_level.txt
zemfrog-5.0.1.dist-info/RECORD
