Metadata-Version: 2.1
Name: zemfrog
Version: 5.0.1
Summary: Zemfrog is a simple framework based on flask for building a REST API quickly.
Home-page: https://github.com/zemfrog/zemfrog
Author: Aprila Hijriyan
Author-email: hijriyan23@gmail.com
License: MIT license
Project-URL: Github, https://github.com/zemfrog/zemfrog
Project-URL: Issue Tracker, https://github.com/zemfrog/zemfrog/issues
Project-URL: Donation, https://www.patreon.com/aprilahijriyan
Keywords: flask wsgi web zemfrog api
Platform: UNKNOWN
Classifier: Development Status :: 4 - Beta
Classifier: Intended Audience :: Developers
Classifier: License :: OSI Approved :: MIT License
Classifier: Natural Language :: English
Classifier: Programming Language :: Python :: 3
Classifier: Programming Language :: Python :: 3.6
Classifier: Programming Language :: Python :: 3.7
Classifier: Programming Language :: Python :: 3.8
Classifier: Framework :: Flask
Requires-Python: >=3.6
Requires-Dist: flask (==1.1.2)
Requires-Dist: flask-smorest
Requires-Dist: flask-sqlalchemy (==2.4.4)
Requires-Dist: flask-jwt-extended (==3.25.0)
Requires-Dist: flask-marshmallow
Requires-Dist: flask-cors (==3.0.9)
Requires-Dist: flask-migrate
Requires-Dist: flask-mail
Requires-Dist: flask-shell-ipython
Requires-Dist: marshmallow-sqlalchemy
Requires-Dist: python-dotenv
Requires-Dist: click
Requires-Dist: celery (==5.0.2)
Requires-Dist: marshmallow
Requires-Dist: sqlalchemy-utils
Requires-Dist: sqlalchemy (<1.4.0)
